txftools/__init__.py
txftools/currency_sorted.py
txftools/encryption.py
txftools/execute_redis.py
txftools/format_data.py
txftools/lazy_test.py
txftools/linux_excute.py
txftools/only_id.py
txftools/pipfile_lock_requirements.py
txftools/province.py
txftools/send_emals.py
txftools/ssh_online.py
txftools/timer.py
txftools-2.3.5.dist-info/LICENSE
txftools-2.3.5.dist-info/METADATA
txftools-2.3.5.dist-info/WHEEL
txftools-2.3.5.dist-info/top_level.txt
txftools-2.3.5.dist-info/zip-safe
txftools-2.3.5.dist-info/RECORD
