Metadata-Version: 2.1
Name: txftools
Version: 2.3.5
Summary: django response middleware
Home-page: https://github.com/txf402066270/txf_tools
Author: wu-di-tian-ge-ge
Author-email: 402066270@qq.com
License: NEU
Classifier: Programming Language :: Python
Classifier: Intended Audience :: Developers
Classifier: Operating System :: OS Independent
License-File: LICENSE
Requires-Dist: django-redis
Requires-Dist: python-dateutil
Requires-Dist: pycryptodomex
Requires-Dist: rsa
